{"categories":[{"id":"5bfa4637-8893-4e48-9b94-d1de14991263","createdAt":1718769683653,"updatedAt":1718769683653,"name":"Sports"},{"id":"08e95315-f5fe-4b91-8baf-c94f7601faea","createdAt":1718769683653,"updatedAt":1718769683653,"name":"Sports"},{"id":"39b49d8d-56c5-4500-ab31-5e2ab92fcb25","createdAt":1718769683653,"updatedAt":1718769683653,"name":"Sports"},{"id":"8cb572d6-5c10-451f-8c69-e1f198b21961","createdAt":1718769683653,"updatedAt":1718769683653,"name":"Sports"},{"id":"c66d0ab5-daa0-4d2d-aa2c-7e915f63effd","createdAt":1718769683653,"updatedAt":1718769683653,"name":"Sports"}],"products":[{"id":"2762da3a-b933-49b7-a377-c00a7745cfb2","categoryId":"5bfa4637-8893-4e48-9b94-d1de14991263","createdAt":1718769683653,"updatedAt":1718769683653,"name":"Gorgeous Plastic Towels","material":"Soft","description":"New ABC 13 9370, 13.3, 5th Gen CoreA5-8250U, 8GB RAM, 256GB SSD, power UHD Graphics, OS 10 Home, OS Office A & J 2016","price":310,"image":"https://picsum.photos/seed/EjEFod/200/300"},{"id":"a8c1016b-2d6a-47cf-bf40-3fa4b8219fd3","categoryId":"5bfa4637-8893-4e48-9b94-d1de14991263","createdAt":1718769683653,"updatedAt":1718769683653,"name":"Gorgeous Plastic Towels","material":"Soft","description":"New ABC 13 9370, 13.3, 5th Gen CoreA5-8250U, 8GB RAM, 256GB SSD, power UHD Graphics, OS 10 Home, OS Office A & J 2016","price":310,"image":"https://picsum.photos/seed/EjEFod/200/300"},{"id":"f5d72dac-17a7-42fc-8164-9bd2778a9aea","categoryId":"5bfa4637-8893-4e48-9b94-d1de14991263","createdAt":1718769683653,"updatedAt":1718769683653,"name":"Gorgeous Plastic Towels","material":"Soft","description":"New ABC 13 9370, 13.3, 5th Gen CoreA5-8250U, 8GB RAM, 256GB SSD, power UHD Graphics, OS 10 Home, OS Office A & J 2016","price":310,"image":"https://picsum.photos/seed/EjEFod/200/300"},{"id":"c16d18e0-f1db-4949-a983-aeeb0f37544b","categoryId":"5bfa4637-8893-4e48-9b94-d1de14991263","createdAt":1718769683653,"updatedAt":1718769683653,"name":"Gorgeous Plastic Towels","material":"Soft","description":"New ABC 13 9370, 13.3, 5th Gen CoreA5-8250U, 8GB RAM, 256GB SSD, power UHD Graphics, OS 10 Home, OS Office A & J 2016","price":310,"image":"https://picsum.photos/seed/EjEFod/200/300"},{"id":"dca0bc44-813a-4da1-b54e-e9c7e8ed9247","categoryId":"5bfa4637-8893-4e48-9b94-d1de14991263","createdAt":1718769683653,"updatedAt":1718769683653,"name":"Gorgeous Plastic Towels","material":"Soft","description":"New ABC 13 9370, 13.3, 5th Gen CoreA5-8250U, 8GB RAM, 256GB SSD, power UHD Graphics, OS 10 Home, OS Office A & J 2016","price":310,"image":"https://picsum.photos/seed/EjEFod/200/300"},{"id":"b6d1b93a-f14a-4c75-bc8a-6b093e3b47cb","categoryId":"08e95315-f5fe-4b91-8baf-c94f7601faea","createdAt":1718769683653,"updatedAt":1718769683653,"name":"Gorgeous Plastic Towels","material":"Soft","description":"New ABC 13 9370, 13.3, 5th Gen CoreA5-8250U, 8GB RAM, 256GB SSD, power UHD Graphics, OS 10 Home, OS Office A & J 2016","price":310,"image":"https://picsum.photos/seed/EjEFod/200/300"},{"id":"7dc39ee1-9115-4f8d-b3c0-4b67052afb68","categoryId":"08e95315-f5fe-4b91-8baf-c94f7601faea","createdAt":1718769683653,"updatedAt":1718769683653,"name":"Gorgeous Plastic Towels","material":"Soft","description":"New ABC 13 9370, 13.3, 5th Gen CoreA5-8250U, 8GB RAM, 256GB SSD, power UHD Graphics, OS 10 Home, OS Office A & J 2016","price":310,"image":"https://picsum.photos/seed/EjEFod/200/300"},{"id":"3c4fff66-3b54-412e-b5e5-e7267217580e","categoryId":"08e95315-f5fe-4b91-8baf-c94f7601faea","createdAt":1718769683653,"updatedAt":1718769683653,"name":"Gorgeous Plastic Towels","material":"Soft","description":"New ABC 13 9370, 13.3, 5th Gen CoreA5-8250U, 8GB RAM, 256GB SSD, power UHD Graphics, OS 10 Home, OS Office A & J 2016","price":310,"image":"https://picsum.photos/seed/EjEFod/200/300"},{"id":"25dd6958-6cb0-4a3b-ade9-c802e03dcf80","categoryId":"08e95315-f5fe-4b91-8baf-c94f7601faea","createdAt":1718769683653,"updatedAt":1718769683653,"name":"Gorgeous Plastic Towels","material":"Soft","description":"New ABC 13 9370, 13.3, 5th Gen CoreA5-8250U, 8GB RAM, 256GB SSD, power UHD Graphics, OS 10 Home, OS Office A & J 2016","price":310,"image":"https://picsum.photos/seed/EjEFod/200/300"},{"id":"9880bf44-8c21-4c39-a4e5-92e85a2b9e7f","categoryId":"08e95315-f5fe-4b91-8baf-c94f7601faea","createdAt":1718769683653,"updatedAt":1718769683653,"name":"Gorgeous Plastic Towels","material":"Soft","description":"New ABC 13 9370, 13.3, 5th Gen CoreA5-8250U, 8GB RAM, 256GB SSD, power UHD Graphics, OS 10 Home, OS Office A & J 2016","price":310,"image":"https://picsum.photos/seed/EjEFod/200/300"},{"id":"eb43db5c-1095-4f25-af83-70a7372e5c27","categoryId":"39b49d8d-56c5-4500-ab31-5e2ab92fcb25","createdAt":1718769683653,"updatedAt":1718769683653,"name":"Gorgeous Plastic Towels","material":"Soft","description":"New ABC 13 9370, 13.3, 5th Gen CoreA5-8250U, 8GB RAM, 256GB SSD, power UHD Graphics, OS 10 Home, OS Office A & J 2016","price":310,"image":"https://picsum.photos/seed/EjEFod/200/300"},{"id":"baa3368a-ecd5-4479-9a7f-09c916e2afc3","categoryId":"39b49d8d-56c5-4500-ab31-5e2ab92fcb25","createdAt":1718769683653,"updatedAt":1718769683653,"name":"Gorgeous Plastic Towels","material":"Soft","description":"New ABC 13 9370, 13.3, 5th Gen CoreA5-8250U, 8GB RAM, 256GB SSD, power UHD Graphics, OS 10 Home, OS Office A & J 2016","price":310,"image":"https://picsum.photos/seed/EjEFod/200/300"},{"id":"f6ad1f4b-5e12-4ba7-a6fe-6a6656c568e8","categoryId":"39b49d8d-56c5-4500-ab31-5e2ab92fcb25","createdAt":1718769683653,"updatedAt":1718769683653,"name":"Gorgeous Plastic Towels","material":"Soft","description":"New ABC 13 9370, 13.3, 5th Gen CoreA5-8250U, 8GB RAM, 256GB SSD, power UHD Graphics, OS 10 Home, OS Office A & J 2016","price":310,"image":"https://picsum.photos/seed/EjEFod/200/300"},{"id":"92c8df38-9417-4e6d-9b21-c9e5abc71dcb","categoryId":"39b49d8d-56c5-4500-ab31-5e2ab92fcb25","createdAt":1718769683653,"updatedAt":1718769683653,"name":"Gorgeous Plastic Towels","material":"Soft","description":"New ABC 13 9370, 13.3, 5th Gen CoreA5-8250U, 8GB RAM, 256GB SSD, power UHD Graphics, OS 10 Home, OS Office A & J 2016","price":310,"image":"https://picsum.photos/seed/EjEFod/200/300"},{"id":"963b644a-ed2b-4065-8035-2a1b4027f785","categoryId":"39b49d8d-56c5-4500-ab31-5e2ab92fcb25","createdAt":1718769683653,"updatedAt":1718769683653,"name":"Gorgeous Plastic Towels","material":"Soft","description":"New ABC 13 9370, 13.3, 5th Gen CoreA5-8250U, 8GB RAM, 256GB SSD, power UHD Graphics, OS 10 Home, OS Office A & J 2016","price":310,"image":"https://picsum.photos/seed/EjEFod/200/300"},{"id":"db10aaa5-83fb-404c-8f57-7e9f288edf87","categoryId":"8cb572d6-5c10-451f-8c69-e1f198b21961","createdAt":1718769683653,"updatedAt":1718769683653,"name":"Gorgeous Plastic Towels","material":"Soft","description":"New ABC 13 9370, 13.3, 5th Gen CoreA5-8250U, 8GB RAM, 256GB SSD, power UHD Graphics, OS 10 Home, OS Office A & J 2016","price":310,"image":"https://picsum.photos/seed/EjEFod/200/300"},{"id":"97834f28-127e-4a10-9dd4-e33924975d4e","categoryId":"8cb572d6-5c10-451f-8c69-e1f198b21961","createdAt":1718769683653,"updatedAt":1718769683653,"name":"Gorgeous Plastic Towels","material":"Soft","description":"New ABC 13 9370, 13.3, 5th Gen CoreA5-8250U, 8GB RAM, 256GB SSD, power UHD Graphics, OS 10 Home, OS Office A & J 2016","price":310,"image":"https://picsum.photos/seed/EjEFod/200/300"},{"id":"43857b24-9336-4353-8632-2d3050fa4744","categoryId":"8cb572d6-5c10-451f-8c69-e1f198b21961","createdAt":1718769683653,"updatedAt":1718769683653,"name":"Gorgeous Plastic Towels","material":"Soft","description":"New ABC 13 9370, 13.3, 5th Gen CoreA5-8250U, 8GB RAM, 256GB SSD, power UHD Graphics, OS 10 Home, OS Office A & J 2016","price":310,"image":"https://picsum.photos/seed/EjEFod/200/300"},{"id":"ee1a5497-fada-4802-a740-fa845fb1ce19","categoryId":"8cb572d6-5c10-451f-8c69-e1f198b21961","createdAt":1718769683653,"updatedAt":1718769683653,"name":"Gorgeous Plastic Towels","material":"Soft","description":"New ABC 13 9370, 13.3, 5th Gen CoreA5-8250U, 8GB RAM, 256GB SSD, power UHD Graphics, OS 10 Home, OS Office A & J 2016","price":310,"image":"https://picsum.photos/seed/EjEFod/200/300"},{"id":"032bb976-eda5-476a-aad2-feb12b5670a1","categoryId":"8cb572d6-5c10-451f-8c69-e1f198b21961","createdAt":1718769683653,"updatedAt":1718769683653,"name":"Gorgeous Plastic Towels","material":"Soft","description":"New ABC 13 9370, 13.3, 5th Gen CoreA5-8250U, 8GB RAM, 256GB SSD, power UHD Graphics, OS 10 Home, OS Office A & J 2016","price":310,"image":"https://picsum.photos/seed/EjEFod/200/300"},{"id":"65f0bc70-8e67-43ac-8cfa-c3982038a032","categoryId":"c66d0ab5-daa0-4d2d-aa2c-7e915f63effd","createdAt":1718769683653,"updatedAt":1718769683653,"name":"Gorgeous Plastic Towels","material":"Soft","description":"New ABC 13 9370, 13.3, 5th Gen CoreA5-8250U, 8GB RAM, 256GB SSD, power UHD Graphics, OS 10 Home, OS Office A & J 2016","price":310,"image":"https://picsum.photos/seed/EjEFod/200/300"},{"id":"9f49f5bd-7d18-49c0-ace8-520b2f88b82e","categoryId":"c66d0ab5-daa0-4d2d-aa2c-7e915f63effd","createdAt":1718769683653,"updatedAt":1718769683653,"name":"Gorgeous Plastic Towels","material":"Soft","description":"New ABC 13 9370, 13.3, 5th Gen CoreA5-8250U, 8GB RAM, 256GB SSD, power UHD Graphics, OS 10 Home, OS Office A & J 2016","price":310,"image":"https://picsum.photos/seed/EjEFod/200/300"},{"id":"5c493b7f-3c4e-4b28-adaf-cf7f0e700425","categoryId":"c66d0ab5-daa0-4d2d-aa2c-7e915f63effd","createdAt":1718769683653,"updatedAt":1718769683653,"name":"Gorgeous Plastic Towels","material":"Soft","description":"New ABC 13 9370, 13.3, 5th Gen CoreA5-8250U, 8GB RAM, 256GB SSD, power UHD Graphics, OS 10 Home, OS Office A & J 2016","price":310,"image":"https://picsum.photos/seed/EjEFod/200/300"},{"id":"8e732326-30f7-41e7-9957-b5e73e2707d2","categoryId":"c66d0ab5-daa0-4d2d-aa2c-7e915f63effd","createdAt":1718769683653,"updatedAt":1718769683653,"name":"Gorgeous Plastic Towels","material":"Soft","description":"New ABC 13 9370, 13.3, 5th Gen CoreA5-8250U, 8GB RAM, 256GB SSD, power UHD Graphics, OS 10 Home, OS Office A & J 2016","price":310,"image":"https://picsum.photos/seed/EjEFod/200/300"},{"id":"efcd0381-5f9d-41a7-87a2-326cd5c5b38a","categoryId":"c66d0ab5-daa0-4d2d-aa2c-7e915f63effd","createdAt":1718769683653,"updatedAt":1718769683653,"name":"Gorgeous Plastic Towels","material":"Soft","description":"New ABC 13 9370, 13.3, 5th Gen CoreA5-8250U, 8GB RAM, 256GB SSD, power UHD Graphics, OS 10 Home, OS Office A & J 2016","price":310,"image":"https://picsum.photos/seed/EjEFod/200/300"}]}